{
  "schemaVersion": 1,
  "missionId": "005-login-success",
  "startUrl": "https://the-internet.herokuapp.com/login",
  "collectFields": [
    "secureAreaH4"
  ],
  "successCheck": "secureAreaH4 == \"Welcome to the Secure Area. When you are done click logout below.\"",
  "rules": [
    {
      "field": "secureAreaH4",
      "op": "eq",
      "value": "Welcome to the Secure Area. When you are done click logout below."
    }
  ],
  "examplePayload": {
    "secureAreaH4": "Welcome to the Secure Area. When you are done click logout below."
  }
}
